afflib/__init__.py
afflib/afflib.py
afflib-0.0.1.dist-info/licenses/LICENSE.txt
afflib-0.0.1.dist-info/METADATA
afflib-0.0.1.dist-info/WHEEL
afflib-0.0.1.dist-info/top_level.txt
afflib-0.0.1.dist-info/RECORD
