Metadata-Version: 2.4
Name: afflib
Version: 0.0.1
Summary: A library for processing charts for game Arcaea
Author: chitake
Author-email: 
License: The Unlicense
Classifier: Development Status :: 7 - Inactive
Classifier: Programming Language :: Python :: 3 :: Only
Classifier: Topic :: File Formats
Classifier: Topic :: Software Development :: Libraries
Classifier: Typing :: Typed
License-File: LICENSE.txt
Dynamic: author
Dynamic: classifier
Dynamic: license
Dynamic: license-file
Dynamic: summary
